data_preprocessing_lib/__init__.py
data_preprocessing_lib/categorical_encoder.py
data_preprocessing_lib/data_type_converter.py
data_preprocessing_lib/datetime_handler.py
data_preprocessing_lib/missing_value_handler.py
data_preprocessing_lib/outlier_handler.py
data_preprocessing_lib/scaler.py
data_preprocessing_lib/text_cleaner.py
tests/__init__.py
tests/test_categorical_encoder.py
tests/test_data_type_converter.py
tests/test_datetime_handler.py
tests/test_missing_value_handler.py
tests/test_outlier_handler.py
tests/test_scaler.py
tests/test_text_cleaner.py
oguzhan_gokcekoca_preprocessing-0.1.dist-info/METADATA
oguzhan_gokcekoca_preprocessing-0.1.dist-info/WHEEL
oguzhan_gokcekoca_preprocessing-0.1.dist-info/top_level.txt
oguzhan_gokcekoca_preprocessing-0.1.dist-info/RECORD
